arr/__init__.py
arr/__main__.py
arr/__version__.py
arr/arr.py
arr/gaia.py
arr/k2.py
arr/kepler.py
arr/reference.py
arr/simbad.py
arr/star.py
arr/tess.py
arr-0.2.1.dist-info/LICENSE
arr-0.2.1.dist-info/METADATA
arr-0.2.1.dist-info/WHEEL
arr-0.2.1.dist-info/entry_points.txt
arr-0.2.1.dist-info/top_level.txt
arr-0.2.1.dist-info/RECORD
