Metadata-Version: 2.1
Name: arr
Version: 0.2.1
Summary: Astronomic Reference Resolver
Home-page: https://github.com/muma7490/ARR
Author: Marco Müllner
Author-email: muellnermarco@gmail.com
License: UNKNOWN
Platform: UNKNOWN
Classifier: Programming Language :: Python :: 3.7
Classifier: Programming Language :: Python :: 3.6
Classifier: License :: OSI Approved :: MIT License
Classifier: Operating System :: OS Independent
